{
  "node_id": "breakwave_insights_insights_2022-08-26_2022_08_27_weekly_dry_market_report__root",
  "doc_id": "breakwave_insights_insights_2022-08-26_2022_08_27_weekly_dry_market_report",
  "parent_id": null,
  "title": "Weekly Dry Market Report",
  "section_path": [
    "Weekly Dry Market Report"
  ],
  "section_path_text": "Weekly Dry Market Report",
  "level": 0,
  "ordinal": 0,
  "summary": "Main\nBy Mark Nugent\n\nLooking towards the winter\nEnergy prices are continuing to firm in Europe and weather is driving supply/demand changes across several regions. We look at how these recent developments shape the outlook for seaborne coal demand going forward. More issues on the way in Australia?",
  "keywords": [
    "china",
    "australia",
    "pacific",
    "europe",
    "coal",
    "gas",
    "july",
    "weather",
    "country",
    "demand",
    "seaborne",
    "tonnes"
  ],
  "page_start": null,
  "page_end": null,
  "token_count": 872,
  "source_path": "reports/breakwave/2022/2022-08-27_weekly-dry-market-report.html",
  "source_url": "https://www.breakwaveadvisors.com/insights/2022/8/26/weekly-dry-market-report",
  "children": [
    {
      "node_id": "breakwave_insights_insights_2022-08-26_2022_08_27_weekly_dry_market_report__s01_main",
      "doc_id": "breakwave_insights_insights_2022-08-26_2022_08_27_weekly_dry_market_report",
      "parent_id": "breakwave_insights_insights_2022-08-26_2022_08_27_weekly_dry_market_report__root",
      "title": "Main",
      "section_path": [
        "Main"
      ],
      "section_path_text": "Main",
      "level": 1,
      "ordinal": 1,
      "summary": "",
      "keywords": [
        "mark",
        "nugent"
      ],
      "page_start": null,
      "page_end": null,
      "token_count": 4,
      "section_type": null,
      "children": []
    },
    {
      "node_id": "breakwave_insights_insights_2022-08-26_2022_08_27_weekly_dry_market_report__s02_looking_towards_the_winter",
      "doc_id": "breakwave_insights_insights_2022-08-26_2022_08_27_weekly_dry_market_report",
      "parent_id": "breakwave_insights_insights_2022-08-26_2022_08_27_weekly_dry_market_report__root",
      "title": "Looking towards the winter",
      "section_path": [
        "Looking towards the winter"
      ],
      "section_path_text": "Looking towards the winter",
      "level": 1,
      "ordinal": 2,
      "summary": "Energy prices are continuing to firm in Europe and weather is driving supply/demand changes across several regions. We look at how these recent developments shape the outlook for seaborne coal demand going forward.",
      "keywords": [
        "europe",
        "coal",
        "are",
        "changes",
        "continuing",
        "demand",
        "developments",
        "driving"
      ],
      "page_start": null,
      "page_end": null,
      "token_count": 39,
      "section_type": null,
      "children": []
    },
    {
      "node_id": "breakwave_insights_insights_2022-08-26_2022_08_27_weekly_dry_market_report__s03_more_issues_on_the_way_in_australia",
      "doc_id": "breakwave_insights_insights_2022-08-26_2022_08_27_weekly_dry_market_report",
      "parent_id": "breakwave_insights_insights_2022-08-26_2022_08_27_weekly_dry_market_report__root",
      "title": "More issues on the way in Australia?",
      "section_path": [
        "More issues on the way in Australia?"
      ],
      "section_path_text": "More issues on the way in Australia?",
      "level": 1,
      "ordinal": 3,
      "summary": "Following the heavily disrupted month of July for Australian coal exports, shipments in August are on track to recover back above 30m tonnes. In July, the extreme weather resulted in the country's lowest level of monthly coal exports on record, amounting to 24.4m tonnes.",
      "keywords": [
        "australia",
        "pacific",
        "coal",
        "july",
        "exports",
        "weather",
        "country",
        "following"
      ],
      "page_start": null,
      "page_end": null,
      "token_count": 185,
      "section_type": null,
      "children": []
    },
    {
      "node_id": "breakwave_insights_insights_2022-08-26_2022_08_27_weekly_dry_market_report__s04_china_drought_disrupting_hydro_output",
      "doc_id": "breakwave_insights_insights_2022-08-26_2022_08_27_weekly_dry_market_report",
      "parent_id": "breakwave_insights_insights_2022-08-26_2022_08_27_weekly_dry_market_report__root",
      "title": "China drought disrupting hydro output",
      "section_path": [
        "China drought disrupting hydro output"
      ],
      "section_path_text": "China drought disrupting hydro output",
      "level": 1,
      "ordinal": 4,
      "summary": "In China, several weather stations along the Yangtze have reportedly recorded their highest ever temperatures in the past week. According to Reuters estimates, hydro-to-coal replacement for the rest of the year in China has increased by 16.2m tonnes versus last month's predictions due to the persistent dryness.",
      "keywords": [
        "china",
        "coal",
        "demand",
        "power",
        "volumes",
        "any",
        "august",
        "black"
      ],
      "page_start": null,
      "page_end": null,
      "token_count": 359,
      "section_type": null,
      "children": []
    },
    {
      "node_id": "breakwave_insights_insights_2022-08-26_2022_08_27_weekly_dry_market_report__s05_rhine_water_levels_back_above_minimum",
      "doc_id": "breakwave_insights_insights_2022-08-26_2022_08_27_weekly_dry_market_report",
      "parent_id": "breakwave_insights_insights_2022-08-26_2022_08_27_weekly_dry_market_report__root",
      "title": "Rhine water levels back above minimum",
      "section_path": [
        "Rhine water levels back above minimum"
      ],
      "section_path_text": "Rhine water levels back above minimum",
      "level": 1,
      "ordinal": 5,
      "summary": "Following weeks of falling water levels on the Rhine, which inherently reduced ARA ports' capacity to discharge coal, some relief has come with wetter weather as the river have returned above the minimum level for barges. Subsequently, coal stocks have started to fall at ports in the region.",
      "keywords": [
        "europe",
        "coal",
        "gas",
        "european",
        "tonnes",
        "come",
        "falling",
        "imports"
      ],
      "page_start": null,
      "page_end": null,
      "token_count": 255,
      "section_type": null,
      "children": []
    }
  ]
}