{
  "node_id": "breakwave_insights_insights_2022-01-13_2022_01_14_recent_developments_in_indian_coal_and_electricity_markets__root",
  "doc_id": "breakwave_insights_insights_2022-01-13_2022_01_14_recent_developments_in_indian_coal_and_electricity_markets",
  "parent_id": null,
  "title": "Recent Developments In Indian Coal And Electricity Markets",
  "section_path": [
    "Recent Developments In Indian Coal And Electricity Markets"
  ],
  "section_path_text": "Recent Developments In Indian Coal And Electricity Markets",
  "level": 0,
  "ordinal": 0,
  "summary": "Main\nBy Jeffrey Landsberg\nCoal India continues to do an admirable job in increasing its coal production. Coal India produced approximately 60.2 million tons of coal last month, which marks a month-on-month increase of 6.4 million tons (12%) and a year-on-year increase of 1.9 million tons (3%). Coal India's production has continued to climb dramatically since September and has continued to lead to a rise in the nation's power plant stockpiles.",
  "keywords": [
    "india",
    "coal",
    "year-on-year",
    "million",
    "tons",
    "last",
    "hours",
    "kilowatt",
    "billion",
    "increase",
    "month-on-month",
    "approximately"
  ],
  "page_start": null,
  "page_end": null,
  "token_count": 509,
  "source_path": "reports/breakwave/2022/2022-01-14_recent-developments-in-indian-coal-and-electricity-markets.html",
  "source_url": "https://www.breakwaveadvisors.com/insights/2022/1/13/recent-developments-in-indian-coal-and-electricity-markets",
  "children": [
    {
      "node_id": "breakwave_insights_insights_2022-01-13_2022_01_14_recent_developments_in_indian_coal_and_electricity_markets__s01_main",
      "doc_id": "breakwave_insights_insights_2022-01-13_2022_01_14_recent_developments_in_indian_coal_and_electricity_markets",
      "parent_id": "breakwave_insights_insights_2022-01-13_2022_01_14_recent_developments_in_indian_coal_and_electricity_markets__root",
      "title": "Main",
      "section_path": [
        "Main"
      ],
      "section_path_text": "Main",
      "level": 1,
      "ordinal": 1,
      "summary": "By Jeffrey Landsberg\nCoal India continues to do an admirable job in increasing its coal production. Coal India produced approximately 60.2 million tons of coal last month, which marks a month-on-month increase of 6.4 million tons (12%) and a year-on-year increase of 1.9 million tons (3%).",
      "keywords": [
        "india",
        "coal",
        "year-on-year",
        "million",
        "tons",
        "last",
        "hours",
        "kilowatt"
      ],
      "page_start": null,
      "page_end": null,
      "token_count": 507,
      "section_type": null,
      "children": []
    }
  ]
}