{
  "node_id": "breakwave_insights_insights_2024-02-06_2024_02_06_202426dry__root",
  "doc_id": "breakwave_insights_insights_2024-02-06_2024_02_06_202426dry",
  "parent_id": null,
  "title": "202426Dry",
  "section_path": [
    "202426Dry"
  ],
  "section_path_text": "202426Dry",
  "level": 0,
  "ordinal": 0,
  "summary": "Main\n· Chinese New Year sees Capesize spot rates at 15-year highs - As the celebrations for the Year of the Dragon are underway in China, Capesize owners have their own milestone to celebrate, with Capesize spot rates at 15-year highs for this time of the year , a period that traditionally had marked the low point for any given year. The Atlantic market remains the main driver of such an astonishing yet surprising performance, while the reasons behind the current strength all point to inadequate vessel supply in the western hemisphere. Although statistics show a trivial impact from the current Red Sea disruption when it comes to dry bulk, it seems that ballasting tonnage has indeed been dislocated (at a time when also the Panama Canal draught is affecting vessel supply), leading to the now months' long vessel shortage in that part of the world.",
  "keywords": [
    "capesize",
    "china",
    "atlantic",
    "iron_ore",
    "coal",
    "crude_oil",
    "year",
    "years",
    "are",
    "economic",
    "vessel",
    "activity"
  ],
  "page_start": null,
  "page_end": null,
  "token_count": 668,
  "source_path": "reports/breakwave/2024/2024-02-06_202426dry.html",
  "source_url": "https://www.breakwaveadvisors.com/insights/202426dry",
  "children": [
    {
      "node_id": "breakwave_insights_insights_2024-02-06_2024_02_06_202426dry__s01_main",
      "doc_id": "breakwave_insights_insights_2024-02-06_2024_02_06_202426dry",
      "parent_id": "breakwave_insights_insights_2024-02-06_2024_02_06_202426dry__root",
      "title": "Main",
      "section_path": [
        "Main"
      ],
      "section_path_text": "Main",
      "level": 1,
      "ordinal": 1,
      "summary": "· Chinese New Year sees Capesize spot rates at 15-year highs - As the celebrations for the Year of the Dragon are underway in China, Capesize owners have their own milestone to celebrate, with Capesize spot rates at 15-year highs for this time of the year , a period that traditionally had marked the low point for any given year. The Atlantic market remains the main driver of such an astonishing yet surprising performance, while the reasons behind the current strength all point to inadequate vessel supply in the western hemisphere.",
      "keywords": [
        "capesize",
        "china",
        "atlantic",
        "iron_ore",
        "coal",
        "crude_oil",
        "year",
        "years"
      ],
      "page_start": null,
      "page_end": null,
      "token_count": 666,
      "section_type": null,
      "children": []
    }
  ]
}