{
  "node_id": "breakwave_insights_insights_2024-02-07_2024_02_07_europes_diesel_supplies__root",
  "doc_id": "breakwave_insights_insights_2024-02-07_2024_02_07_europes_diesel_supplies",
  "parent_id": null,
  "title": "Europes Diesel Supplies",
  "section_path": [
    "Europes Diesel Supplies"
  ],
  "section_path_text": "Europes Diesel Supplies",
  "level": 0,
  "ordinal": 0,
  "summary": "Main\nBy Chara Georgousi\nHouthi attacks on Red Sea have significantly disrupted the global oil markets, elevating security concerns and leading to increased shipping costs. These incidents have necessitated a reassessment of strategies for transporting oil, with notable implications for the global supply and pricing of diesel fuel. Amidst these tensions, European markets are proactively seeking to mitigate risks by improving logistical strategies and exploring alternative sources for diesel supply.",
  "keywords": [
    "capesize",
    "meg",
    "europe",
    "crude_oil",
    "products",
    "diesel",
    "increase",
    "supply",
    "data",
    "energy",
    "global",
    "imports"
  ],
  "page_start": null,
  "page_end": null,
  "token_count": 695,
  "source_path": "reports/breakwave/2024/2024-02-07_europes-diesel-supplies.html",
  "source_url": "https://www.breakwaveadvisors.com/insights/2024/2/7/europes-diesel-supplies",
  "children": [
    {
      "node_id": "breakwave_insights_insights_2024-02-07_2024_02_07_europes_diesel_supplies__s01_main",
      "doc_id": "breakwave_insights_insights_2024-02-07_2024_02_07_europes_diesel_supplies",
      "parent_id": "breakwave_insights_insights_2024-02-07_2024_02_07_europes_diesel_supplies__root",
      "title": "Main",
      "section_path": [
        "Main"
      ],
      "section_path_text": "Main",
      "level": 1,
      "ordinal": 1,
      "summary": "By Chara Georgousi\nHouthi attacks on Red Sea have significantly disrupted the global oil markets, elevating security concerns and leading to increased shipping costs. These incidents have necessitated a reassessment of strategies for transporting oil, with notable implications for the global supply and pricing of diesel fuel.",
      "keywords": [
        "capesize",
        "meg",
        "europe",
        "crude_oil",
        "products",
        "diesel",
        "increase",
        "supply"
      ],
      "page_start": null,
      "page_end": null,
      "token_count": 693,
      "section_type": null,
      "children": []
    }
  ]
}