{
  "node_id": "breakwave_insights_insights_2024-09-11_2024_09_11_panamaxes_on_the_go__root",
  "doc_id": "breakwave_insights_insights_2024-09-11_2024_09_11_panamaxes_on_the_go",
  "parent_id": null,
  "title": "Panamaxes on the go",
  "section_path": [
    "Panamaxes on the go"
  ],
  "section_path_text": "Panamaxes on the go",
  "level": 0,
  "ordinal": 0,
  "summary": "Main\nThe Baltic Dry Index gave up Monday's gains yesterday as the fortunes of the capesizes faded. Still, the panamaxes provided some offset as the segment's freight indicator recorded a second session of gains. The trading screens for the commodities were dominated by red during yesterday's session, as concerns over the demand outlook contributed to losses in many cases.",
  "keywords": [
    "capesize",
    "panamax",
    "supramax",
    "handysize",
    "lng",
    "lpg",
    "china",
    "atlantic",
    "pacific",
    "europe",
    "india",
    "us_gulf"
  ],
  "page_start": null,
  "page_end": null,
  "token_count": 1727,
  "source_path": "reports/breakwave/2024/2024-09-11_panamaxes-on-the-go.html",
  "source_url": "https://www.breakwaveadvisors.com/insights/2024/9/11/panamaxes-on-the-go",
  "children": [
    {
      "node_id": "breakwave_insights_insights_2024-09-11_2024_09_11_panamaxes_on_the_go__s01_main",
      "doc_id": "breakwave_insights_insights_2024-09-11_2024_09_11_panamaxes_on_the_go",
      "parent_id": "breakwave_insights_insights_2024-09-11_2024_09_11_panamaxes_on_the_go__root",
      "title": "Main",
      "section_path": [
        "Main"
      ],
      "section_path_text": "Main",
      "level": 1,
      "ordinal": 1,
      "summary": "The Baltic Dry Index gave up Monday's gains yesterday as the fortunes of the capesizes faded. Still, the panamaxes provided some offset as the segment's freight indicator recorded a second session of gains.",
      "keywords": [
        "capesize",
        "panamax",
        "supramax",
        "handysize",
        "lng",
        "lpg",
        "china",
        "atlantic"
      ],
      "page_start": null,
      "page_end": null,
      "token_count": 1412,
      "section_type": null,
      "children": []
    },
    {
      "node_id": "breakwave_insights_insights_2024-09-11_2024_09_11_panamaxes_on_the_go__s02_linked_asset_2024_09_11_panamaxes_on_the_go_img_241_c1bc6a9c305a_png",
      "doc_id": "breakwave_insights_insights_2024-09-11_2024_09_11_panamaxes_on_the_go",
      "parent_id": "breakwave_insights_insights_2024-09-11_2024_09_11_panamaxes_on_the_go__root",
      "title": "Linked asset: 2024-09-11_panamaxes-on-the-go_img_241_c1bc6a9c305a.png",
      "section_path": [
        "Linked asset: 2024-09-11_panamaxes-on-the-go_img_241_c1bc6a9c305a.png"
      ],
      "section_path_text": "Linked asset: 2024-09-11_panamaxes-on-the-go_img_241_c1bc6a9c305a.png",
      "level": 1,
      "ordinal": 2,
      "summary": "Source asset: reports/breakwave/2024/assets/2024-09-11_panamaxes-on-the-go_img_241_c1bc6a9c305a.png\n\nLinked image asset: 2024-09-11_panamaxes-on-the-go_img_241_c1bc6a9c305a.png\n\nImage metadata: PNG 1120x633 mode=RGBA\n\nEmbedded info:\ndpi: (95.9866, 95.9866)\n\nOCR text:\nWeekly Cargo Order Volumes (TCT & Voyage) and Vessel Supply for Supramaxes by Basin\nSupply - Indian Ocean (RHS) ™ Supply - Pacific (RHS) ™ Supply - Atlantic (RHS) ™ Indian Ocean @ Pacific ™ Atlantic\n80 250\n\\ ‘ 200\n60 \\\ni |\nMAN | oc othAMin pha alle? } Wiel | R :\n: iin VICTIM tN\n5 40 aM h Ar } WY q ly s\n§ i Y i f i] 10 65\n= 5\nz\n20\n50\n0 0\noP A po?",
      "keywords": [
        "panamax",
        "supramax",
        "atlantic",
        "pacific",
        "india",
        "supply",
        "rhs",
        "asset"
      ],
      "page_start": null,
      "page_end": null,
      "token_count": 282,
      "section_type": "linked_image_asset",
      "children": []
    }
  ]
}