{
  "node_id": "breakwave_insights_insights_2024-09-19_2024_09_19_solid_week_for_dry_bulk_market_last_week_but_fleet_continues__root",
  "doc_id": "breakwave_insights_insights_2024-09-19_2024_09_19_solid_week_for_dry_bulk_market_last_week_but_fleet_continues",
  "parent_id": null,
  "title": "Solid Week For Dry Bulk Market Last Week But Fleet Continues To Grow",
  "section_path": [
    "Solid Week For Dry Bulk Market Last Week But Fleet Continues To Grow"
  ],
  "section_path_text": "Solid Week For Dry Bulk Market Last Week But Fleet Continues To Grow",
  "level": 0,
  "ordinal": 0,
  "summary": "Main\nBy Jeffrey Landsberg\nDry bulk rates were mixed last week, with panamax and supramax rates rising while capesize and handysize rates declined. Capesize rates ended last week averaging $25,620/day, which marked a week-on-week decline of $2,212 (-8%). Panamax rates ended last week averaging $12,849/day, which marked a week-on-week increase of $1,204 (10%).",
  "keywords": [
    "capesize",
    "panamax",
    "supramax",
    "handysize",
    "china",
    "brazil",
    "iron_ore",
    "coal",
    "grain",
    "steel",
    "million",
    "last"
  ],
  "page_start": null,
  "page_end": null,
  "token_count": 607,
  "source_path": "reports/breakwave/2024/2024-09-19_solid-week-for-dry-bulk-market-last-week-but-fleet-continues.html",
  "source_url": "https://www.breakwaveadvisors.com/insights/2024/9/19/solid-week-for-dry-bulk-market-last-week-but-fleet-continues-to-grow",
  "children": [
    {
      "node_id": "breakwave_insights_insights_2024-09-19_2024_09_19_solid_week_for_dry_bulk_market_last_week_but_fleet_continues__s01_main",
      "doc_id": "breakwave_insights_insights_2024-09-19_2024_09_19_solid_week_for_dry_bulk_market_last_week_but_fleet_continues",
      "parent_id": "breakwave_insights_insights_2024-09-19_2024_09_19_solid_week_for_dry_bulk_market_last_week_but_fleet_continues__root",
      "title": "Main",
      "section_path": [
        "Main"
      ],
      "section_path_text": "Main",
      "level": 1,
      "ordinal": 1,
      "summary": "By Jeffrey Landsberg\nDry bulk rates were mixed last week, with panamax and supramax rates rising while capesize and handysize rates declined. Capesize rates ended last week averaging $25,620/day, which marked a week-on-week decline of $2,212 (-8%).",
      "keywords": [
        "capesize",
        "panamax",
        "supramax",
        "handysize",
        "china",
        "brazil",
        "iron_ore",
        "coal"
      ],
      "page_start": null,
      "page_end": null,
      "token_count": 605,
      "section_type": null,
      "children": []
    }
  ]
}