{
  "node_id": "breakwave_insights_insights_2026-01-28_2026_01_28_energy_markets_on_edge_amid_supply_risks__root",
  "doc_id": "breakwave_insights_insights_2026-01-28_2026_01_28_energy_markets_on_edge_amid_supply_risks",
  "parent_id": null,
  "title": "Energy Markets On Edge Amid Supply Risks",
  "section_path": [
    "Energy Markets On Edge Amid Supply Risks"
  ],
  "section_path_text": "Energy Markets On Edge Amid Supply Risks",
  "level": 0,
  "ordinal": 0,
  "summary": "Main\nPrecious metals recorded gains amid strong investor interest. Energy markets remain on edge, as supply risks rose. By Daniel Hynes\n\nMarket Commentary\nGold pushed higher, consolidating gains above USD5,000/oz, as investors look ahead to the upcoming Fed rate decision.",
  "keywords": [
    "lng",
    "china",
    "brazil",
    "europe",
    "iron_ore",
    "crude_oil",
    "steel",
    "gas",
    "prices",
    "ahead",
    "are",
    "demand"
  ],
  "page_start": null,
  "page_end": null,
  "token_count": 745,
  "source_path": "reports/breakwave/2026/2026-01-28_energy-markets-on-edge-amid-supply-risks.html",
  "source_url": "https://www.breakwaveadvisors.com/insights/2026/1/28/energy-markets-on-edge-amid-supply-risks",
  "children": [
    {
      "node_id": "breakwave_insights_insights_2026-01-28_2026_01_28_energy_markets_on_edge_amid_supply_risks__s01_main",
      "doc_id": "breakwave_insights_insights_2026-01-28_2026_01_28_energy_markets_on_edge_amid_supply_risks",
      "parent_id": "breakwave_insights_insights_2026-01-28_2026_01_28_energy_markets_on_edge_amid_supply_risks__root",
      "title": "Main",
      "section_path": [
        "Main"
      ],
      "section_path_text": "Main",
      "level": 1,
      "ordinal": 1,
      "summary": "Precious metals recorded gains amid strong investor interest. Energy markets remain on edge, as supply risks rose.",
      "keywords": [
        "amid",
        "daniel",
        "demand",
        "edge",
        "energy",
        "gains",
        "hynes",
        "interest."
      ],
      "page_start": null,
      "page_end": null,
      "token_count": 32,
      "section_type": null,
      "children": []
    },
    {
      "node_id": "breakwave_insights_insights_2026-01-28_2026_01_28_energy_markets_on_edge_amid_supply_risks__s02_market_commentary",
      "doc_id": "breakwave_insights_insights_2026-01-28_2026_01_28_energy_markets_on_edge_amid_supply_risks",
      "parent_id": "breakwave_insights_insights_2026-01-28_2026_01_28_energy_markets_on_edge_amid_supply_risks__root",
      "title": "Market Commentary",
      "section_path": [
        "Market Commentary"
      ],
      "section_path_text": "Market Commentary",
      "level": 1,
      "ordinal": 2,
      "summary": "Gold pushed higher, consolidating gains above USD5,000/oz, as investors look ahead to the upcoming Fed rate decision. A pause after three consecutive cuts remains the consensus view, however data overnight provide some reasons why we don't expect an extended pause.",
      "keywords": [
        "lng",
        "china",
        "brazil",
        "europe",
        "iron_ore",
        "crude_oil",
        "steel",
        "gas"
      ],
      "page_start": null,
      "page_end": null,
      "token_count": 638,
      "section_type": null,
      "children": []
    },
    {
      "node_id": "breakwave_insights_insights_2026-01-28_2026_01_28_energy_markets_on_edge_amid_supply_risks__s03_chart_of_the_day",
      "doc_id": "breakwave_insights_insights_2026-01-28_2026_01_28_energy_markets_on_edge_amid_supply_risks",
      "parent_id": "breakwave_insights_insights_2026-01-28_2026_01_28_energy_markets_on_edge_amid_supply_risks__root",
      "title": "Chart of the Day",
      "section_path": [
        "Chart of the Day"
      ],
      "section_path_text": "Chart of the Day",
      "level": 1,
      "ordinal": 3,
      "summary": "China's steel industry continues to suffer from overcapacity amid weak demand. Utilisation at steel mills has been failing in recent years.",
      "keywords": [
        "china",
        "steel",
        "amid",
        "averaged",
        "capacity",
        "closure",
        "commodities",
        "continues"
      ],
      "page_start": null,
      "page_end": null,
      "token_count": 64,
      "section_type": null,
      "children": []
    }
  ]
}