{
  "node_id": "hellenic_demolition_2024-02-05_2024_02_05_gms_week_05_fractured__root",
  "doc_id": "hellenic_demolition_2024-02-05_2024_02_05_gms_week_05_fractured",
  "parent_id": null,
  "title": "GMS Week 05 - FRACTURED!",
  "section_path": [
    "GMS Week 05 - FRACTURED!"
  ],
  "section_path_text": "GMS Week 05 - FRACTURED!",
  "level": 0,
  "ordinal": 0,
  "summary": "Main\nDespite both Bangladeshi and Pakistani markets making noticeable improvements over recent weeks,unfortunately, the ongoing shortage in the global availability of ‘market' tonnage has ensured sales remain noticeably extricated, which has in turn restricted the industry's ability at assessing where levels really stand today. As evident from the number of arrivals & beachings this week (see Indian sub-continent port reports on Page 8), an increasing number of Ship Recyclers have clearly managed to and are reportedly still in the process of obtaining further approvals on L/Cs from their respective banks. As a result, there is now a noticeable disparity in offers emanating from recyclers from the same sub-continent destination, so fractured is the sub-continent ship recycling purview on the immediate future of fundamentals & vessel pricing across the board.",
  "keywords": [
    "panamax",
    "lpg",
    "container",
    "china",
    "europe",
    "india",
    "singapore",
    "japan",
    "grain",
    "crude_oil",
    "steel",
    "gas"
  ],
  "page_start": null,
  "page_end": null,
  "token_count": 5789,
  "source_path": "reports/hellenic/demolition/2024/2024-02-05_gms-week-05-fractured.html",
  "source_url": "https://www.hellenicshippingnews.com/gms-week-05-fractured",
  "children": [
    {
      "node_id": "hellenic_demolition_2024-02-05_2024_02_05_gms_week_05_fractured__s01_main",
      "doc_id": "hellenic_demolition_2024-02-05_2024_02_05_gms_week_05_fractured",
      "parent_id": "hellenic_demolition_2024-02-05_2024_02_05_gms_week_05_fractured__root",
      "title": "Main",
      "section_path": [
        "Main"
      ],
      "section_path_text": "Main",
      "level": 1,
      "ordinal": 1,
      "summary": "Despite both Bangladeshi and Pakistani markets making noticeable improvements over recent weeks,unfortunately, the ongoing shortage in the global availability of ‘market' tonnage has ensured sales remain noticeably extricated, which has in turn restricted the industry's ability at assessing where levels really stand today. As evident from the number of arrivals & beachings this week (see Indian sub-continent port reports on Page 8), an increasing number of Ship Recyclers have clearly managed to and are reportedly still in the process of obtaining further approvals on L/Cs from their respective banks.",
      "keywords": [
        "china",
        "europe",
        "india",
        "steel",
        "number",
        "are",
        "recycling",
        "ship"
      ],
      "page_start": null,
      "page_end": null,
      "token_count": 580,
      "section_type": null,
      "children": []
    },
    {
      "node_id": "hellenic_demolition_2024-02-05_2024_02_05_gms_week_05_fractured__s02_linked_asset_2024_02_05_gms_week_05_fractured_ship_recycling_market_insight_week_0_a96b91a6f086_pdf",
      "doc_id": "hellenic_demolition_2024-02-05_2024_02_05_gms_week_05_fractured",
      "parent_id": "hellenic_demolition_2024-02-05_2024_02_05_gms_week_05_fractured__root",
      "title": "Linked asset: 2024-02-05_gms-week-05-fractured_ship-recycling-market-insight-week-0_a96b91a6f086.pdf",
      "section_path": [
        "Linked asset: 2024-02-05_gms-week-05-fractured_ship-recycling-market-insight-week-0_a96b91a6f086.pdf"
      ],
      "section_path_text": "Linked asset: 2024-02-05_gms-week-05-fractured_ship-recycling-market-insight-week-0_a96b91a6f086.pdf",
      "level": 1,
      "ordinal": 2,
      "summary": "Source asset: reports/hellenic/demolition/pdfs/2024-02-05_gms-week-05-fractured_ship-recycling-market-insight-week-0_a96b91a6f086.pdf\n\n[Page 1]\nI\n, l'\n-+Ali / +N\nFebruary 2nd, 2024 \"You are in danger of living a life so comfortable and soft that you will\nVolume 258, Issue 1120 die without ever realizing your true potential.\"\nWeek 5\n- David Goggins (Google him)\nHighlights: MARKET COMMENTARY\n\"There are only t\nF\nw\nR\no o\nA\npt\nC\nio\nT\nns\nU\nre\nR\nga\nE\nrd\nD\nin\n! You're either in or\nyou're out.",
      "keywords": [
        "panamax",
        "lpg",
        "container",
        "china",
        "europe",
        "india",
        "singapore",
        "japan"
      ],
      "page_start": null,
      "page_end": null,
      "token_count": 4985,
      "section_type": "linked_pdf",
      "children": []
    },
    {
      "node_id": "hellenic_demolition_2024-02-05_2024_02_05_gms_week_05_fractured__s03_linked_asset_2024_02_05_gms_week_05_fractured_img1_24856_ec2fa1a34262_jpg",
      "doc_id": "hellenic_demolition_2024-02-05_2024_02_05_gms_week_05_fractured",
      "parent_id": "hellenic_demolition_2024-02-05_2024_02_05_gms_week_05_fractured__root",
      "title": "Linked asset: 2024-02-05_gms-week-05-fractured_img1_24856_ec2fa1a34262.jpg",
      "section_path": [
        "Linked asset: 2024-02-05_gms-week-05-fractured_img1_24856_ec2fa1a34262.jpg"
      ],
      "section_path_text": "Linked asset: 2024-02-05_gms-week-05-fractured_img1_24856_ec2fa1a34262.jpg",
      "level": 1,
      "ordinal": 3,
      "summary": "Source asset: reports/hellenic/demolition/2024/assets/2024-02-05_gms-week-05-fractured_img1_24856_ec2fa1a34262.jpg\n\nLinked image asset: 2024-02-05_gms-week-05-fractured_img1_24856_ec2fa1a34262.jpg\n\nImage metadata: JPEG 696x177 mode=RGB\n\nEmbedded info:\ndpi: (120, 120)\n\nOCR text:\nRank _Location Sentiment na oteom danke || one\nUSD/LDT USD/LDT USD/LDT\n| 4 | Turkey | Weak ~~ | 340/LDT_| 350/LDT | 360/LDT |",
      "keywords": [
        "ldt",
        "usd/ldt",
        "asset",
        "image",
        "danke",
        "dpi",
        "embedded",
        "gms-week-05-fractured_img1_24856_ec2fa1a34262.jpg"
      ],
      "page_start": null,
      "page_end": null,
      "token_count": 151,
      "section_type": "linked_image_asset",
      "children": []
    }
  ]
}