{
  "node_id": "breakwave_insights_insights_2025-02-14_2025_02_14_dirty_oil_supply__root",
  "doc_id": "breakwave_insights_insights_2025-02-14_2025_02_14_dirty_oil_supply",
  "parent_id": null,
  "title": "Dirty Oil Supply",
  "section_path": [
    "Dirty Oil Supply"
  ],
  "section_path_text": "Dirty Oil Supply",
  "level": 0,
  "ordinal": 0,
  "summary": "Main\nTanker - Weekly Market Monitor\nSnapshot of Crude and Product Freight Rates, Supply-Demand\nWeek 07, February 14, 2025\nBy early 2025, net supply has declined significantly from the peaks seen in 2023 and early 2024, reinforcing the inverse correlation between supply levels and TD3 rates. The sharp drop in net supply has driven a notable spike in TD3 rates, validating the fundamental supply-demand pricing mechanism in the VLCC market. A major supply peak in mid-2023 (~180 vessels) led to subdued TD3 rates, but recent volatility in Baltic TD3 rates suggests a strengthening trend, particularly if crude oil demand remains resilient.",
  "keywords": [
    "capesize",
    "panamax",
    "vlcc",
    "suezmax",
    "aframax",
    "china",
    "atlantic",
    "meg",
    "west_africa",
    "europe",
    "india",
    "us_gulf"
  ],
  "page_start": null,
  "page_end": null,
  "token_count": 1148,
  "source_path": "reports/breakwave/2025/2025-02-14_dirty-oil-supply.html",
  "source_url": "https://www.breakwaveadvisors.com/insights/2025/2/14/dirty-oil-supply",
  "children": [
    {
      "node_id": "breakwave_insights_insights_2025-02-14_2025_02_14_dirty_oil_supply__s01_main",
      "doc_id": "breakwave_insights_insights_2025-02-14_2025_02_14_dirty_oil_supply",
      "parent_id": "breakwave_insights_insights_2025-02-14_2025_02_14_dirty_oil_supply__root",
      "title": "Main",
      "section_path": [
        "Main"
      ],
      "section_path_text": "Main",
      "level": 1,
      "ordinal": 1,
      "summary": "Tanker - Weekly Market Monitor\nSnapshot of Crude and Product Freight Rates, Supply-Demand\nWeek 07, February 14, 2025\nBy early 2025, net supply has declined significantly from the peaks seen in 2023 and early 2024, reinforcing the inverse correlation between supply levels and TD3 rates. The sharp drop in net supply has driven a notable spike in TD3 rates, validating the fundamental supply-demand pricing mechanism in the VLCC market.",
      "keywords": [
        "capesize",
        "panamax",
        "vlcc",
        "suezmax",
        "aframax",
        "china",
        "atlantic",
        "meg"
      ],
      "page_start": null,
      "page_end": null,
      "token_count": 1146,
      "section_type": null,
      "children": []
    }
  ]
}